clirun/__init__.py
clirun/google.py
clirun-0.0.1.dist-info/LICENSE
clirun-0.0.1.dist-info/METADATA
clirun-0.0.1.dist-info/WHEEL
clirun-0.0.1.dist-info/RECORD
